{
  "packWeights": {
    "regular": 30,
    "solid": 20,
    "brands": 5,
    "unknown": 0
  },
  "tokenExactMatch": 12,
  "tokenPartialMatch": 4,
  "stateTokenBonus": 3,
  "conceptKeywordMatch": 16,
  "toggleOppositionBonus": 8,
  "brandBoostForBrandIntent": 18,
  "brandsPenaltyForNonBrandIntent": -8,
  "concepts": {
    "playback": ["play", "pause", "stop", "next", "previous", "skip", "media"],
    "audio": ["mute", "unmute", "volume", "sound", "speaker", "mic", "microphone"],
    "view": ["grid", "list", "gallery", "view", "layout", "tiles"],
    "navigation": ["up", "down", "left", "right", "back", "forward", "home"],
    "editing": ["copy", "paste", "cut", "undo", "redo", "indent", "unindent", "format"],
    "brightness": ["brightness", "dim", "light", "dark"],
    "power": ["power", "sleep", "wake", "shutdown"],
    "connectivity": ["wifi", "bluetooth", "network", "airplane"],
    "brand": ["github", "slack", "spotify", "dropbox", "google", "microsoft", "youtube", "notion"]
  }
}
